{"nodes": [{"id": "src_ai_provider_voiceassistantprovider_jsx", "label": "VoiceAssistantProvider.jsx", "file_type": "code", "source_file": "src\\ai\\provider\\VoiceAssistantProvider.jsx", "source_location": "L1"}, {"id": "voiceassistantprovider_usevoiceassistant", "label": "useVoiceAssistant()", "file_type": "code", "source_file": "src\\ai\\provider\\VoiceAssistantProvider.jsx", "source_location": "L46"}, {"id": "voiceassistantprovider_voiceassistantprovider", "label": "VoiceAssistantProvider()", "file_type": "code", "source_file": "src\\ai\\provider\\VoiceAssistantProvider.jsx", "source_location": "L57"}], "edges": [{"source": "src_ai_provider_voiceassistantprovider_jsx", "target": "react", "relation": "imports_from", "confidence": "EXTRACTED", "source_file": "src\\ai\\provider\\VoiceAssistantProvider.jsx", "source_location": "L16", "weight": 1.0}, {"source": "src_ai_provider_voiceassistantprovider_jsx", "target": "react_router_dom", "relation": "imports_from", "confidence": "EXTRACTED", "source_file": "src\\ai\\provider\\VoiceAssistantProvider.jsx", "source_location": "L20", "weight": 1.0}, {"source": "src_ai_provider_voiceassistantprovider_jsx", "target": "react_i18next", "relation": "imports_from", "confidence": "EXTRACTED", "source_file": "src\\ai\\provider\\VoiceAssistantProvider.jsx", "source_location": "L21", "weight": 1.0}, {"source": "src_ai_provider_voiceassistantprovider_jsx", "target": "src_ai_brain_aiengine_ts", "relation": "imports_from", "confidence": "EXTRACTED", "source_file": "src\\ai\\provider\\VoiceAssistantProvider.jsx", "source_location": "L24", "weight": 1.0}, {"source": "src_ai_provider_voiceassistantprovider_jsx", "target": "src_ai_voice_speechrecognition_ts", "relation": "imports_from", "confidence": "EXTRACTED", "source_file": "src\\ai\\provider\\VoiceAssistantProvider.jsx", "source_location": "L26", "weight": 1.0}, {"source": "src_ai_provider_voiceassistantprovider_jsx", "target": "src_ai_voice_speechsynthesis_ts", "relation": "imports_from", "confidence": "EXTRACTED", "source_file": "src\\ai\\provider\\VoiceAssistantProvider.jsx", "source_location": "L27", "weight": 1.0}, {"source": "src_ai_provider_voiceassistantprovider_jsx", "target": "src_ai_voice_wakeword_ts", "relation": "imports_from", "confidence": "EXTRACTED", "source_file": "src\\ai\\provider\\VoiceAssistantProvider.jsx", "source_location": "L28", "weight": 1.0}, {"source": "src_ai_provider_voiceassistantprovider_jsx", "target": "src_ai_voice_transcriptmanager_ts", "relation": "imports_from", "confidence": "EXTRACTED", "source_file": "src\\ai\\provider\\VoiceAssistantProvider.jsx", "source_location": "L29", "weight": 1.0}, {"source": "src_ai_provider_voiceassistantprovider_jsx", "target": "src_ai_voice_audiomanager_ts", "relation": "imports_from", "confidence": "EXTRACTED", "source_file": "src\\ai\\provider\\VoiceAssistantProvider.jsx", "source_location": "L30", "weight": 1.0}, {"source": "src_ai_provider_voiceassistantprovider_jsx", "target": "src_ai_brain_intentrouter_ts", "relation": "imports_from", "confidence": "EXTRACTED", "source_file": "src\\ai\\provider\\VoiceAssistantProvider.jsx", "source_location": "L32", "weight": 1.0}, {"source": "src_ai_provider_voiceassistantprovider_jsx", "target": "src_ai_actions_formactions_ts", "relation": "imports_from", "confidence": "EXTRACTED", "source_file": "src\\ai\\provider\\VoiceAssistantProvider.jsx", "source_location": "L33", "weight": 1.0}, {"source": "src_ai_provider_voiceassistantprovider_jsx", "target": "src_ai_actions_navigationactions_ts", "relation": "imports_from", "confidence": "EXTRACTED", "source_file": "src\\ai\\provider\\VoiceAssistantProvider.jsx", "source_location": "L34", "weight": 1.0}, {"source": "src_ai_provider_voiceassistantprovider_jsx", "target": "src_ai_actions_uiactions_ts", "relation": "imports_from", "confidence": "EXTRACTED", "source_file": "src\\ai\\provider\\VoiceAssistantProvider.jsx", "source_location": "L35", "weight": 1.0}, {"source": "src_ai_provider_voiceassistantprovider_jsx", "target": "src_ai_actions_kioskactions_ts", "relation": "imports_from", "confidence": "EXTRACTED", "source_file": "src\\ai\\provider\\VoiceAssistantProvider.jsx", "source_location": "L36", "weight": 1.0}, {"source": "src_ai_provider_voiceassistantprovider_jsx", "target": "src_ai_actions_accessibilityactions_ts", "relation": "imports_from", "confidence": "EXTRACTED", "source_file": "src\\ai\\provider\\VoiceAssistantProvider.jsx", "source_location": "L37", "weight": 1.0}, {"source": "src_ai_provider_voiceassistantprovider_jsx", "target": "src_ai_brain_multilingualprocessor_ts", "relation": "imports_from", "confidence": "EXTRACTED", "source_file": "src\\ai\\provider\\VoiceAssistantProvider.jsx", "source_location": "L39", "weight": 1.0}, {"source": "src_ai_provider_voiceassistantprovider_jsx", "target": "src_ai_brain_conversationmanager_ts", "relation": "imports_from", "confidence": "EXTRACTED", "source_file": "src\\ai\\provider\\VoiceAssistantProvider.jsx", "source_location": "L40", "weight": 1.0}, {"source": "src_ai_provider_voiceassistantprovider_jsx", "target": "voiceassistantprovider_usevoiceassistant", "relation": "contains", "confidence": "EXTRACTED", "source_file": "src\\ai\\provider\\VoiceAssistantProvider.jsx", "source_location": "L46", "weight": 1.0}, {"source": "src_ai_provider_voiceassistantprovider_jsx", "target": "voiceassistantprovider_voiceassistantprovider", "relation": "contains", "confidence": "EXTRACTED", "source_file": "src\\ai\\provider\\VoiceAssistantProvider.jsx", "source_location": "L57", "weight": 1.0}], "raw_calls": [{"caller_nid": "voiceassistantprovider_usevoiceassistant", "callee": "useContext", "source_file": "src\\ai\\provider\\VoiceAssistantProvider.jsx", "source_location": "L47"}, {"caller_nid": "voiceassistantprovider_voiceassistantprovider", "callee": "useNavigate", "source_file": "src\\ai\\provider\\VoiceAssistantProvider.jsx", "source_location": "L58"}, {"caller_nid": "voiceassistantprovider_voiceassistantprovider", "callee": "useLocation", "source_file": "src\\ai\\provider\\VoiceAssistantProvider.jsx", "source_location": "L59"}, {"caller_nid": "voiceassistantprovider_voiceassistantprovider", "callee": "useTranslation", "source_file": "src\\ai\\provider\\VoiceAssistantProvider.jsx", "source_location": "L60"}, {"caller_nid": "voiceassistantprovider_voiceassistantprovider", "callee": "useState", "source_file": "src\\ai\\provider\\VoiceAssistantProvider.jsx", "source_location": "L62"}, {"caller_nid": "voiceassistantprovider_voiceassistantprovider", "callee": "useState", "source_file": "src\\ai\\provider\\VoiceAssistantProvider.jsx", "source_location": "L63"}, {"caller_nid": "voiceassistantprovider_voiceassistantprovider", "callee": "useState", "source_file": "src\\ai\\provider\\VoiceAssistantProvider.jsx", "source_location": "L64"}, {"caller_nid": "voiceassistantprovider_voiceassistantprovider", "callee": "useState", "source_file": "src\\ai\\provider\\VoiceAssistantProvider.jsx", "source_location": "L65"}, {"caller_nid": "voiceassistantprovider_voiceassistantprovider", "callee": "useState", "source_file": "src\\ai\\provider\\VoiceAssistantProvider.jsx", "source_location": "L66"}, {"caller_nid": "voiceassistantprovider_voiceassistantprovider", "callee": "useState", "source_file": "src\\ai\\provider\\VoiceAssistantProvider.jsx", "source_location": "L67"}, {"caller_nid": "voiceassistantprovider_voiceassistantprovider", "callee": "useState", "source_file": "src\\ai\\provider\\VoiceAssistantProvider.jsx", "source_location": "L68"}, {"caller_nid": "voiceassistantprovider_voiceassistantprovider", "callee": "useState", "source_file": "src\\ai\\provider\\VoiceAssistantProvider.jsx", "source_location": "L69"}, {"caller_nid": "voiceassistantprovider_voiceassistantprovider", "callee": "useRef", "source_file": "src\\ai\\provider\\VoiceAssistantProvider.jsx", "source_location": "L71"}, {"caller_nid": "voiceassistantprovider_voiceassistantprovider", "callee": "useRef", "source_file": "src\\ai\\provider\\VoiceAssistantProvider.jsx", "source_location": "L72"}, {"caller_nid": "voiceassistantprovider_voiceassistantprovider", "callee": "getCurrentLanguage", "source_file": "src\\ai\\provider\\VoiceAssistantProvider.jsx", "source_location": "L72"}, {"caller_nid": "voiceassistantprovider_voiceassistantprovider", "callee": "useRef", "source_file": "src\\ai\\provider\\VoiceAssistantProvider.jsx", "source_location": "L73"}, {"caller_nid": "voiceassistantprovider_voiceassistantprovider", "callee": "useRef", "source_file": "src\\ai\\provider\\VoiceAssistantProvider.jsx", "source_location": "L74"}, {"caller_nid": "voiceassistantprovider_voiceassistantprovider", "callee": "useCallback", "source_file": "src\\ai\\provider\\VoiceAssistantProvider.jsx", "source_location": "L83"}, {"caller_nid": "voiceassistantprovider_voiceassistantprovider", "callee": "useCallback", "source_file": "src\\ai\\provider\\VoiceAssistantProvider.jsx", "source_location": "L94"}, {"caller_nid": "voiceassistantprovider_voiceassistantprovider", "callee": "useCallback", "source_file": "src\\ai\\provider\\VoiceAssistantProvider.jsx", "source_location": "L121"}, {"caller_nid": "voiceassistantprovider_voiceassistantprovider", "callee": "useCallback", "source_file": "src\\ai\\provider\\VoiceAssistantProvider.jsx", "source_location": "L128"}, {"caller_nid": "voiceassistantprovider_voiceassistantprovider", "callee": "useCallback", "source_file": "src\\ai\\provider\\VoiceAssistantProvider.jsx", "source_location": "L161"}, {"caller_nid": "voiceassistantprovider_voiceassistantprovider", "callee": "useCallback", "source_file": "src\\ai\\provider\\VoiceAssistantProvider.jsx", "source_location": "L206"}, {"caller_nid": "voiceassistantprovider_voiceassistantprovider", "callee": "useCallback", "source_file": "src\\ai\\provider\\VoiceAssistantProvider.jsx", "source_location": "L217"}, {"caller_nid": "voiceassistantprovider_voiceassistantprovider", "callee": "useEffect", "source_file": "src\\ai\\provider\\VoiceAssistantProvider.jsx", "source_location": "L293"}, {"caller_nid": "voiceassistantprovider_voiceassistantprovider", "callee": "useCallback", "source_file": "src\\ai\\provider\\VoiceAssistantProvider.jsx", "source_location": "L306"}, {"caller_nid": "voiceassistantprovider_voiceassistantprovider", "callee": "useCallback", "source_file": "src\\ai\\provider\\VoiceAssistantProvider.jsx", "source_location": "L336"}, {"caller_nid": "voiceassistantprovider_voiceassistantprovider", "callee": "useCallback", "source_file": "src\\ai\\provider\\VoiceAssistantProvider.jsx", "source_location": "L352"}, {"caller_nid": "voiceassistantprovider_voiceassistantprovider", "callee": "useCallback", "source_file": "src\\ai\\provider\\VoiceAssistantProvider.jsx", "source_location": "L363"}, {"caller_nid": "voiceassistantprovider_voiceassistantprovider", "callee": "useCallback", "source_file": "src\\ai\\provider\\VoiceAssistantProvider.jsx", "source_location": "L371"}, {"caller_nid": "voiceassistantprovider_voiceassistantprovider", "callee": "useEffect", "source_file": "src\\ai\\provider\\VoiceAssistantProvider.jsx", "source_location": "L380"}, {"caller_nid": "voiceassistantprovider_voiceassistantprovider", "callee": "useEffect", "source_file": "src\\ai\\provider\\VoiceAssistantProvider.jsx", "source_location": "L395"}, {"caller_nid": "voiceassistantprovider_voiceassistantprovider", "callee": "useEffect", "source_file": "src\\ai\\provider\\VoiceAssistantProvider.jsx", "source_location": "L402"}, {"caller_nid": "voiceassistantprovider_voiceassistantprovider", "callee": "useEffect", "source_file": "src\\ai\\provider\\VoiceAssistantProvider.jsx", "source_location": "L428"}, {"caller_nid": "voiceassistantprovider_voiceassistantprovider", "callee": "currentLanguage", "source_file": "src\\ai\\provider\\VoiceAssistantProvider.jsx", "source_location": "L457"}]}