{"nodes": [{"id": "src_ai_brain_promptbuilder_js", "label": "promptBuilder.js", "file_type": "code", "source_file": "src\\ai\\brain\\promptBuilder.js", "source_location": "L1"}, {"id": "promptbuilder_getrelevantknowledge", "label": "getRelevantKnowledge()", "file_type": "code", "source_file": "src\\ai\\brain\\promptBuilder.js", "source_location": "L23"}, {"id": "promptbuilder_buildmessages", "label": "buildMessages()", "file_type": "code", "source_file": "src\\ai\\brain\\promptBuilder.js", "source_location": "L61"}, {"id": "promptbuilder_buildlitemessages", "label": "buildLiteMessages()", "file_type": "code", "source_file": "src\\ai\\brain\\promptBuilder.js", "source_location": "L104"}, {"id": "promptbuilder_buildformextractionprompt", "label": "buildFormExtractionPrompt()", "file_type": "code", "source_file": "src\\ai\\brain\\promptBuilder.js", "source_location": "L117"}], "edges": [{"source": "src_ai_brain_promptbuilder_js", "target": "src_ai_prompts_systemprompt_ts", "relation": "imports_from", "confidence": "EXTRACTED", "source_file": "src\\ai\\brain\\promptBuilder.js", "source_location": "L12", "weight": 1.0}, {"source": "src_ai_brain_promptbuilder_js", "target": "src_ai_prompts_serviceknowledge_ts", "relation": "imports_from", "confidence": "EXTRACTED", "source_file": "src\\ai\\brain\\promptBuilder.js", "source_location": "L13", "weight": 1.0}, {"source": "src_ai_brain_promptbuilder_js", "target": "src_ai_brain_contextmemory_ts", "relation": "imports_from", "confidence": "EXTRACTED", "source_file": "src\\ai\\brain\\promptBuilder.js", "source_location": "L14", "weight": 1.0}, {"source": "src_ai_brain_promptbuilder_js", "target": "promptbuilder_getrelevantknowledge", "relation": "contains", "confidence": "EXTRACTED", "source_file": "src\\ai\\brain\\promptBuilder.js", "source_location": "L23", "weight": 1.0}, {"source": "src_ai_brain_promptbuilder_js", "target": "promptbuilder_buildmessages", "relation": "contains", "confidence": "EXTRACTED", "source_file": "src\\ai\\brain\\promptBuilder.js", "source_location": "L61", "weight": 1.0}, {"source": "src_ai_brain_promptbuilder_js", "target": "promptbuilder_buildlitemessages", "relation": "contains", "confidence": "EXTRACTED", "source_file": "src\\ai\\brain\\promptBuilder.js", "source_location": "L104", "weight": 1.0}, {"source": "src_ai_brain_promptbuilder_js", "target": "promptbuilder_buildformextractionprompt", "relation": "contains", "confidence": "EXTRACTED", "source_file": "src\\ai\\brain\\promptBuilder.js", "source_location": "L117", "weight": 1.0}, {"source": "promptbuilder_buildmessages", "target": "promptbuilder_getrelevantknowledge", "relation": "calls", "confidence": "EXTRACTED", "source_file": "src\\ai\\brain\\promptBuilder.js", "source_location": "L75", "weight": 1.0}], "raw_calls": [{"caller_nid": "promptbuilder_getrelevantknowledge", "callee": "buildKnowledgeSummary", "source_file": "src\\ai\\brain\\promptBuilder.js", "source_location": "L46"}, {"caller_nid": "promptbuilder_buildmessages", "callee": "getContextSummary", "source_file": "src\\ai\\brain\\promptBuilder.js", "source_location": "L68"}, {"caller_nid": "promptbuilder_buildmessages", "callee": "getMessagesForAPI", "source_file": "src\\ai\\brain\\promptBuilder.js", "source_location": "L69"}, {"caller_nid": "promptbuilder_buildmessages", "callee": "push", "source_file": "src\\ai\\brain\\promptBuilder.js", "source_location": "L95"}, {"caller_nid": "promptbuilder_buildformextractionprompt", "callee": "join", "source_file": "src\\ai\\brain\\promptBuilder.js", "source_location": "L118"}]}